lib_dep_pkg_insomniapx/__init__.py
lib_dep_pkg_insomniapx/file0.py
lib_dep_pkg_insomniapx/folder1/__init__.py
lib_dep_pkg_insomniapx/folder1/file1.py
lib_dep_pkg_insomniapx/folder1/subfolder1/__init__.py
lib_dep_pkg_insomniapx/folder1/subfolder1/file3.py
lib_dep_pkg_insomniapx/folder2/__init__.py
lib_dep_pkg_insomniapx/folder2/file2.py
dependency_package_insomniapx-0.0.2.dist-info/LICENSE
dependency_package_insomniapx-0.0.2.dist-info/METADATA
dependency_package_insomniapx-0.0.2.dist-info/WHEEL
dependency_package_insomniapx-0.0.2.dist-info/top_level.txt
dependency_package_insomniapx-0.0.2.dist-info/RECORD
